blocks/__init__.py
blocks/core.py
blocks/dfio.py
blocks/utils.py
blocks/filesystem/__init__.py
blocks/filesystem/base.py
blocks/filesystem/gcs_filesystem.py
blocks/filesystem/gcs_native_filesystem.py
tests/__init__.py
tests/conftest.py
tests/test_access.py
tests/test_assemble.py
tests/test_divide.py
tests/test_filesystem.py
tests/test_iterate.py
tests/test_partitioned.py
tests/test_pickle.py
tests/test_place.py
sq_blocks-0.9.4.dist-info/LICENSE.txt
sq_blocks-0.9.4.dist-info/METADATA
sq_blocks-0.9.4.dist-info/WHEEL
sq_blocks-0.9.4.dist-info/top_level.txt
sq_blocks-0.9.4.dist-info/RECORD
