Metadata-Version: 2.1
Name: sq-blocks
Version: 0.9.4
Summary: Blocks provides a simple interface to read, organize, and manipulate structured data in files on local and cloud storage
Home-page: UNKNOWN
Author: Bradley Axen
Author-email: baxen@squareup.com
License: UNKNOWN
Keywords: blocks
Platform: UNKNOWN
Classifier: Intended Audience :: Developers
Classifier: Natural Language :: English
Classifier: Programming Language :: Python :: 3
Requires-Dist: pandas
Requires-Dist: fsspec (>=2021.7.0)
Requires-Dist: gcsfs (>=2021.7.0)
Requires-Dist: s3fs
Requires-Dist: pyarrow
Requires-Dist: fastavro
Requires-Dist: wrapt
Provides-Extra: dev
Requires-Dist: flake8 ; extra == 'dev'
Requires-Dist: delegator.py ; extra == 'dev'
Requires-Dist: pre-commit ; extra == 'dev'
Requires-Dist: sphinx ; extra == 'dev'
Requires-Dist: furo ; extra == 'dev'
Requires-Dist: numpydoc ; extra == 'dev'
Requires-Dist: sphinx-copybutton ; extra == 'dev'
Requires-Dist: pytest-cov ; extra == 'dev'
Requires-Dist: pytest ; extra == 'dev'
Provides-Extra: doc
Requires-Dist: sphinx ; extra == 'doc'
Requires-Dist: numpydoc ; extra == 'doc'
Requires-Dist: furo ; extra == 'doc'
Requires-Dist: sphinx-copybutton ; extra == 'doc'
Provides-Extra: format
Requires-Dist: pre-commit ; extra == 'format'
Provides-Extra: tests
Requires-Dist: pytest ; extra == 'tests'
Requires-Dist: pytest-cov ; extra == 'tests'
Requires-Dist: delegator.py ; extra == 'tests'
Requires-Dist: flake8 ; extra == 'tests'
